noqaexplain-0.1.0.dist-info/METADATA
noqaexplain-0.1.0.dist-info/WHEEL
noqaexplain-0.1.0.dist-info/entry_points.txt
noqaexplain/__init__.py
noqaexplain/_cli.py
noqaexplain/_default.py
noqaexplain/_match.py
noqaexplain/_rule.py
noqaexplain/py.typed
noqaexplain/py.typed.license
noqaexplain-0.1.0.dist-info/RECORD
