Metadata-Version: 2.4
Name: noqaexplain
Version: 0.1.0
Summary: Comply or explain - justify every ignored linting rule.
Author: open-nudge
Maintainer: open-nudge
License-Expression: Apache-2.0
Classifier: Development Status :: 2 - Pre-Alpha
Classifier: Intended Audience :: Developers
Classifier: Programming Language :: Python
Classifier: Programming Language :: Python :: 3 :: Only
Classifier: Programming Language :: Python :: 3.12
Classifier: Programming Language :: Python :: 3.13
Classifier: Programming Language :: Python :: 3.14
Classifier: Topic :: Software Development :: Libraries
Classifier: Topic :: Software Development :: Libraries :: Python Modules
Classifier: Typing :: Typed
Project-URL: Changelog, https://github.com/open-nudge/noqaexplain/blob/master/CHANGELOG.md
Project-URL: Documentation, https://open-nudge.github.io/noqaexplain
Project-URL: Homepage, https://open-nudge.github.io/noqaexplain
Project-URL: Issues, https://github.com/open-nudge/noqaexplain/issues
Project-URL: Repository, https://github.com/open-nudge/noqaexplain
Requires-Python: >=3.12
Requires-Dist: lintkit[rich]>=1.1.1
Requires-Dist: loadfig>=0.1.0
